Skills_Utils-0.4.0.dist-info/DESCRIPTION.rst
Skills_Utils-0.4.0.dist-info/METADATA
Skills_Utils-0.4.0.dist-info/RECORD
Skills_Utils-0.4.0.dist-info/WHEEL
Skills_Utils-0.4.0.dist-info/metadata.json
Skills_Utils-0.4.0.dist-info/top_level.txt
skills_utils/__init__.py
skills_utils/common.py
skills_utils/es.py
skills_utils/fs.py
skills_utils/hash.py
skills_utils/io.py
skills_utils/iteration.py
skills_utils/job_posting_import.py
skills_utils/metta.py
skills_utils/s3.py
skills_utils/testing.py
skills_utils/time.py
