Metadata-Version: 2.0
Name: Skills-Utils
Version: 0.4.0
Summary: Shared utilities for skills/jobs taxonomy creation
Home-page: https://github.com/workforce-data-initiative/skills-utils
Author: Center for Data Science and Public Policy
Author-email: datascifellows@gmail.com
License: MIT license
Platform: UNKNOWN
Classifier: Development Status :: 2 - Pre-Alpha
Classifier: Intended Audience :: Developers
Classifier: License :: OSI Approved :: MIT License
Classifier: Natural Language :: English
Classifier: Programming Language :: Python :: 3
Classifier: Programming Language :: Python :: 3.4
Requires-Dist: s3fs
